conciliate/__init__.py
conciliate/__main__.py
conciliate/cli.py
conciliate/config.py
conciliate/diff_engine.py
conciliate/mcp_server.py
conciliate/mock_server.py
conciliate/server.py
conciliate/source_manager.py
conciliate/spec_generator.py
conciliate/summarizer.py
conciliate/watcher.py
conciliate-0.6.0.dist-info/licenses/LICENSE
conciliate-0.6.0.dist-info/METADATA
conciliate-0.6.0.dist-info/WHEEL
conciliate-0.6.0.dist-info/entry_points.txt
conciliate-0.6.0.dist-info/top_level.txt
conciliate-0.6.0.dist-info/RECORD
