Metadata-Version: 2.4
Name: conciliate
Version: 0.6.0
Summary: AI context synchronization and propagation between dev environments
Author: Conciliate Team
License: MIT
Project-URL: Homepage, https://github.com/iv4n-ga6l/conciliate
Project-URL: Repository, https://github.com/iv4n-ga6l/conciliate
Keywords: api,openapi,sync,ai,context,fastapi
Classifier: Development Status :: 3 - Alpha
Classifier: Intended Audience :: Developers
Classifier: License :: OSI Approved :: MIT License
Classifier: Programming Language :: Python :: 3
Classifier: Programming Language :: Python :: 3.9
Classifier: Programming Language :: Python :: 3.10
Classifier: Programming Language :: Python :: 3.11
Classifier: Programming Language :: Python :: 3.12
Requires-Python: >=3.9
License-File: LICENSE
Requires-Dist: fastapi>=0.104.0
Requires-Dist: uvicorn[standard]>=0.24.0
Requires-Dist: watchfiles>=0.21.0
Requires-Dist: deepdiff>=6.7.0
Requires-Dist: typer>=0.9.0
Requires-Dist: pyyaml>=6.0
Requires-Dist: httpx>=0.25.0
Requires-Dist: rich>=13.7.0
Requires-Dist: pydantic>=2.5.0
Requires-Dist: pydantic-settings>=2.1.0
Requires-Dist: mcp>=1.0.0
Requires-Dist: faker>=20.0.0
Provides-Extra: dev
Requires-Dist: pytest>=7.4.0; extra == "dev"
Requires-Dist: pytest-asyncio>=0.21.0; extra == "dev"
Requires-Dist: black>=23.0.0; extra == "dev"
Requires-Dist: ruff>=0.1.0; extra == "dev"
Requires-Dist: mypy>=1.7.0; extra == "dev"
Dynamic: license-file
